divide_region_into_rectangles/LICENSE
divide_region_into_rectangles/README.MD
divide_region_into_rectangles/__init__.py
divide_region_into_rectangles/requirements.txt
divide_region_into_rectangles/thirdparty.json
divide_region_into_rectangles-0.10.dist-info/LICENSE.rst
divide_region_into_rectangles-0.10.dist-info/METADATA
divide_region_into_rectangles-0.10.dist-info/WHEEL
divide_region_into_rectangles-0.10.dist-info/top_level.txt
divide_region_into_rectangles-0.10.dist-info/RECORD
